SimpleDataQualityAnalyzer/__init__.py
SimpleDataQualityAnalyzer/DomainObjects/AnalyzeOptions.py
SimpleDataQualityAnalyzer/DomainObjects/Column.py
SimpleDataQualityAnalyzer/DomainObjects/Report.py
SimpleDataQualityAnalyzer/DomainObjects/__init__.py
SimpleDataQualityAnalyzer/Services/Analyzer.py
SimpleDataQualityAnalyzer/Services/__init__.py
SimpleDataQualityAnalyzer/Services/Templates/functions.js
SimpleDataQualityAnalyzer/Services/Templates/template.html
SimpleDataQualityAnalyzer-1.0.0.4.dist-info/LICENSE
SimpleDataQualityAnalyzer-1.0.0.4.dist-info/METADATA
SimpleDataQualityAnalyzer-1.0.0.4.dist-info/WHEEL
SimpleDataQualityAnalyzer-1.0.0.4.dist-info/top_level.txt
SimpleDataQualityAnalyzer-1.0.0.4.dist-info/RECORD
