Metadata-Version: 2.1
Name: SimpleDataQualityAnalyzer
Version: 1.0.0.4
Summary: A python package that analyzes CSV files and generates a symple HTML report with some summary statistics.
Home-page: https://gitlab.com/debugair/simpledataqualityanalyzer
Author: Stefan Kaspar
Author-email: me@fullbox.ch
License: UNKNOWN
Platform: UNKNOWN
Classifier: Programming Language :: Python :: 3
Classifier: License :: OSI Approved :: MIT License
Classifier: Operating System :: OS Independent
Requires-Python: >=3.6
